{
  "repo": "smilinTux/skwhisper",
  "branch": "main",
  "path": "docs",
  "generated": "2026-07-13",
  "note": "Committed fallback for the /docs viewer when the GitHub Contents API is unavailable or rate-limited. Regenerate from: python docs-manifest-gen.py smilinTux/skwhisper --out docs-manifest.json",
  "docs": [
    {
      "name": "ARCHITECTURE.md",
      "title": "SKWhisper — Architecture"
    },
    {
      "name": "EXAMPLES.md",
      "title": "SKWhisper — Examples & Usage Guide 🌙"
    }
  ]
}
